[
  {
    "symbol": "POWER/USDT",
    "period": "15m",
    "cooldown_minutes": 30,
    "orb_stages": [5, 15, 30]
  },
  {
    "symbol": "BLUAI/USDT",
    "period": "15m",
    "cooldown_minutes": 30,
    "orb_stages": [5, 15, 30]
  },
  {
    "symbol": "IRYS/USDT",
    "period": "15m",
    "cooldown_minutes": 30,
    "orb_stages": [5, 15, 30]
  },
  {
    "symbol": "ON/USDT",
    "period": "15m",
    "cooldown_minutes": 30,
    "orb_stages": [5, 15, 30]
  },
  {
    "symbol": "CLO/USDT",
    "period": "15m",
    "cooldown_minutes": 30,
    "orb_stages": [5, 15, 30]
  },
  {
    "symbol": "APR/USDT",
    "period": "15m",
    "cooldown_minutes": 30,
    "orb_stages": [5, 15, 30]
  },
  {
    "symbol": "RLS/USDT",
    "period": "15m",
    "cooldown_minutes": 30,
    "orb_stages": [5, 15, 30]
  }
]
